<?xml version="1.0" encoding="UTF-8"?><record_update table="sys_app_scan_variable">
    <sys_app_scan_variable action="DELETE">
        <name>sys_id_10186</name>
        <original_value>192391f8d1e70e10a2999780aeddd2a8</original_value>
        <referenced_table>sys_app</referenced_table>
        <run_script>false</run_script>
        <scan_instance>4d763b0d7fafce10695bf4e3c4753e1d</scan_instance>
        <scan_source>scan</scan_source>
        <source_id>7504eafcff5a42103ca0f6648c4fd9d8</source_id>
        <sys_class_name>sys_app_scan_variable</sys_class_name>
        <sys_created_by>jspirko</sys_created_by>
        <sys_created_on>2024-07-19 23:53:38</sys_created_on>
        <sys_id>d7a2627cf5e34e103e2fbb22e00f71f5</sys_id>
        <sys_mod_count>2</sys_mod_count>
        <sys_name>sys_id_10186</sys_name>
        <sys_package display_value="Pub Sector - DHS Service Desk" source="x_snc_pub_sub_dh_1">56042efcff5a42103ca0f6648c4fd93a</sys_package>
        <sys_policy/>
        <sys_scope display_value="Pub Sector - DHS Service Desk">56042efcff5a42103ca0f6648c4fd93a</sys_scope>
        <sys_update_name>sys_app_scan_variable_d7a2627cf5e34e103e2fbb22e00f71f5</sys_update_name>
        <sys_updated_by>jspirko</sys_updated_by>
        <sys_updated_on>2024-07-21 00:40:48</sys_updated_on>
        <template_execution_script/>
        <type display_value="Reference">242d82a65bea101001fb0c370581c7ea</type>
        <variable_hash>e834e4268c04713c463f0fb7e76b4732ecc3cf644a901e4a89b83bffcc7a0482</variable_hash>
    </sys_app_scan_variable>
    <sys_update_version action="INSERT_OR_UPDATE">
        <action>DELETE</action>
        <application display_value="Pub Sector - DHS Service Desk">56042efcff5a42103ca0f6648c4fd93a</application>
        <file_path/>
        <instance_id>76bfb9f61ba9f594fe1b43f4bd4bcb74</instance_id>
        <instance_name>dsforum</instance_name>
        <name>sys_app_scan_variable_d7a2627cf5e34e103e2fbb22e00f71f5</name>
        <payload><![CDATA[<?xml version="1.0" encoding="UTF-8"?><record_update table="sys_app_scan_variable"><sys_app_scan_variable action="INSERT_OR_UPDATE"><name>sys_id_10186</name><original_value>192391f8d1e70e10a2999780aeddd2a8</original_value><referenced_table>sys_app</referenced_table><run_script>false</run_script><scan_instance>4d763b0d7fafce10695bf4e3c4753e1d</scan_instance><scan_source>scan</scan_source><source_id>7504eafcff5a42103ca0f6648c4fd9d8</source_id><sys_class_name>sys_app_scan_variable</sys_class_name><sys_created_by>jspirko</sys_created_by><sys_created_on>2024-07-19 23:53:38</sys_created_on><sys_id>d7a2627cf5e34e103e2fbb22e00f71f5</sys_id><sys_mod_count>2</sys_mod_count><sys_name>sys_id_10186</sys_name><sys_package display_value="Pub Sector - DHS Service Desk" source="x_snc_pub_sub_dh_1">56042efcff5a42103ca0f6648c4fd93a</sys_package><sys_policy/><sys_scope display_value="Pub Sector - DHS Service Desk">56042efcff5a42103ca0f6648c4fd93a</sys_scope><sys_update_name>sys_app_scan_variable_d7a2627cf5e34e103e2fbb22e00f71f5</sys_update_name><sys_updated_by>jspirko</sys_updated_by><sys_updated_on>2024-07-21 00:40:48</sys_updated_on><template_execution_script/><type display_value="Reference">242d82a65bea101001fb0c370581c7ea</type><variable_hash>e834e4268c04713c463f0fb7e76b4732ecc3cf644a901e4a89b83bffcc7a0482</variable_hash></sys_app_scan_variable></record_update>]]></payload>
        <payload_hash>1766352407</payload_hash>
        <record_name>sys_id_10186</record_name>
        <reverted_from/>
        <source>92042efcff5a42103ca0f6648c4fd93c</source>
        <source_table>sys_update_set</source_table>
        <state>previous</state>
        <sys_created_by>jspirko</sys_created_by>
        <sys_created_on>2024-07-21 00:40:48</sys_created_on>
        <sys_id>4017fb01ebefce105204f635cad0cdbf</sys_id>
        <sys_mod_count>0</sys_mod_count>
        <sys_recorded_at>190d2bbe9690000001</sys_recorded_at>
        <sys_updated_by>jspirko</sys_updated_by>
        <sys_updated_on>2024-07-21 00:40:48</sys_updated_on>
        <type>Variable</type>
        <update_guid>4417fb01abefce10f63a5d112b9c37be</update_guid>
        <update_guid_history>4417fb01abefce10f63a5d112b9c37be:1766352407,f40c27855febce10e11e822d3720a88b:-1824854029,d7a2627ce7e34e10c074cff960d0e2f6:1830493580</update_guid_history>
    </sys_update_version>
    <sys_metadata_delete action="INSERT_OR_UPDATE">
        <sys_audit_delete/>
        <sys_class_name>sys_metadata_delete</sys_class_name>
        <sys_created_by>jspirko</sys_created_by>
        <sys_created_on>2024-07-21 16:46:21</sys_created_on>
        <sys_db_object display_value="" name="sys_app_scan_variable">sys_app_scan_variable</sys_db_object>
        <sys_id>8b8372fac5f8432c82dd9cf0ad81a764</sys_id>
        <sys_metadata>d7a2627cf5e34e103e2fbb22e00f71f5</sys_metadata>
        <sys_mod_count>0</sys_mod_count>
        <sys_name>sys_id_10186</sys_name>
        <sys_package display_value="Pub Sector - DHS Service Desk" source="x_snc_pub_sub_dh_1">56042efcff5a42103ca0f6648c4fd93a</sys_package>
        <sys_parent/>
        <sys_policy/>
        <sys_scope display_value="Pub Sector - DHS Service Desk">56042efcff5a42103ca0f6648c4fd93a</sys_scope>
        <sys_scope_delete display_value="">27b1535901ac4ad4a151d045cd3ad1a1</sys_scope_delete>
        <sys_update_name>sys_app_scan_variable_d7a2627cf5e34e103e2fbb22e00f71f5</sys_update_name>
        <sys_update_version display_value="sys_app_scan_variable_d7a2627cf5e34e103e2fbb22e00f71f5">4017fb01ebefce105204f635cad0cdbf</sys_update_version>
        <sys_updated_by>jspirko</sys_updated_by>
        <sys_updated_on>2024-07-21 16:46:21</sys_updated_on>
    </sys_metadata_delete>
</record_update>
