<?xml version="1.0" encoding="UTF-8"?><record_update table="sys_app_scan_variable">
    <sys_app_scan_variable action="DELETE">
        <name>sys_id_9320</name>
        <original_value>04b7f130002f0e10f93f8f839d8aba06</original_value>
        <referenced_table>sys_app</referenced_table>
        <run_script>false</run_script>
        <scan_instance>4d763b0d7fafce10695bf4e3c4753e1d</scan_instance>
        <scan_source>scan</scan_source>
        <source_id>7504eafcff5a42103ca0f6648c4fd9d8</source_id>
        <sys_class_name>sys_app_scan_variable</sys_class_name>
        <sys_created_by>jspirko</sys_created_by>
        <sys_created_on>2024-07-19 23:52:43</sys_created_on>
        <sys_id>3172e2f8afe34e10c176e9cea63baa5f</sys_id>
        <sys_mod_count>2</sys_mod_count>
        <sys_name>sys_id_9320</sys_name>
        <sys_package display_value="Pub Sector - DHS Service Desk" source="x_snc_pub_sub_dh_1">56042efcff5a42103ca0f6648c4fd93a</sys_package>
        <sys_policy/>
        <sys_scope display_value="Pub Sector - DHS Service Desk">56042efcff5a42103ca0f6648c4fd93a</sys_scope>
        <sys_update_name>sys_app_scan_variable_3172e2f8afe34e10c176e9cea63baa5f</sys_update_name>
        <sys_updated_by>jspirko</sys_updated_by>
        <sys_updated_on>2024-07-21 00:39:46</sys_updated_on>
        <template_execution_script/>
        <type display_value="Reference">242d82a65bea101001fb0c370581c7ea</type>
        <variable_hash>407faae1dc94cb6968b38155964c0476d443340780b42470f889b56dde22a007</variable_hash>
    </sys_app_scan_variable>
    <sys_update_version action="INSERT_OR_UPDATE">
        <action>DELETE</action>
        <application display_value="Pub Sector - DHS Service Desk">56042efcff5a42103ca0f6648c4fd93a</application>
        <file_path/>
        <instance_id>76bfb9f61ba9f594fe1b43f4bd4bcb74</instance_id>
        <instance_name>dsforum</instance_name>
        <name>sys_app_scan_variable_3172e2f8afe34e10c176e9cea63baa5f</name>
        <payload><![CDATA[<?xml version="1.0" encoding="UTF-8"?><record_update table="sys_app_scan_variable"><sys_app_scan_variable action="INSERT_OR_UPDATE"><name>sys_id_9320</name><original_value>04b7f130002f0e10f93f8f839d8aba06</original_value><referenced_table>sys_app</referenced_table><run_script>false</run_script><scan_instance>4d763b0d7fafce10695bf4e3c4753e1d</scan_instance><scan_source>scan</scan_source><source_id>7504eafcff5a42103ca0f6648c4fd9d8</source_id><sys_class_name>sys_app_scan_variable</sys_class_name><sys_created_by>jspirko</sys_created_by><sys_created_on>2024-07-19 23:52:43</sys_created_on><sys_id>3172e2f8afe34e10c176e9cea63baa5f</sys_id><sys_mod_count>2</sys_mod_count><sys_name>sys_id_9320</sys_name><sys_package display_value="Pub Sector - DHS Service Desk" source="x_snc_pub_sub_dh_1">56042efcff5a42103ca0f6648c4fd93a</sys_package><sys_policy/><sys_scope display_value="Pub Sector - DHS Service Desk">56042efcff5a42103ca0f6648c4fd93a</sys_scope><sys_update_name>sys_app_scan_variable_3172e2f8afe34e10c176e9cea63baa5f</sys_update_name><sys_updated_by>jspirko</sys_updated_by><sys_updated_on>2024-07-21 00:39:46</sys_updated_on><template_execution_script/><type display_value="Reference">242d82a65bea101001fb0c370581c7ea</type><variable_hash>407faae1dc94cb6968b38155964c0476d443340780b42470f889b56dde22a007</variable_hash></sys_app_scan_variable></record_update>]]></payload>
        <payload_hash>-723014237</payload_hash>
        <record_name>sys_id_9320</record_name>
        <reverted_from/>
        <source>92042efcff5a42103ca0f6648c4fd93c</source>
        <source_table>sys_update_set</source_table>
        <state>previous</state>
        <sys_created_by>jspirko</sys_created_by>
        <sys_created_on>2024-07-21 00:39:46</sys_created_on>
        <sys_id>b0d673cdebafce105204f635cad0cdf7</sys_id>
        <sys_mod_count>0</sys_mod_count>
        <sys_recorded_at>190d2baf6660000001</sys_recorded_at>
        <sys_updated_by>jspirko</sys_updated_by>
        <sys_updated_on>2024-07-21 00:39:46</sys_updated_on>
        <type>Variable</type>
        <update_guid>b4d673cd01afce108ce79d3c0fbdfcf6</update_guid>
        <update_guid_history>b4d673cd01afce108ce79d3c0fbdfcf6:-723014237,82cbab0565ebce108fffe116b282a847:130971719,3172e2f8bee34e1088d19c62b11ee560:248886158</update_guid_history>
    </sys_update_version>
    <sys_metadata_delete action="INSERT_OR_UPDATE">
        <sys_audit_delete/>
        <sys_class_name>sys_metadata_delete</sys_class_name>
        <sys_created_by>jspirko</sys_created_by>
        <sys_created_on>2024-07-21 16:34:53</sys_created_on>
        <sys_db_object display_value="" name="sys_app_scan_variable">sys_app_scan_variable</sys_db_object>
        <sys_id>18868ac6f4304e938751c4f50c327849</sys_id>
        <sys_metadata>3172e2f8afe34e10c176e9cea63baa5f</sys_metadata>
        <sys_mod_count>0</sys_mod_count>
        <sys_name>sys_id_9320</sys_name>
        <sys_package display_value="Pub Sector - DHS Service Desk" source="x_snc_pub_sub_dh_1">56042efcff5a42103ca0f6648c4fd93a</sys_package>
        <sys_parent/>
        <sys_policy/>
        <sys_scope display_value="Pub Sector - DHS Service Desk">56042efcff5a42103ca0f6648c4fd93a</sys_scope>
        <sys_scope_delete display_value="">27b1535901ac4ad4a151d045cd3ad1a1</sys_scope_delete>
        <sys_update_name>sys_app_scan_variable_3172e2f8afe34e10c176e9cea63baa5f</sys_update_name>
        <sys_update_version display_value="sys_app_scan_variable_3172e2f8afe34e10c176e9cea63baa5f">b0d673cdebafce105204f635cad0cdf7</sys_update_version>
        <sys_updated_by>jspirko</sys_updated_by>
        <sys_updated_on>2024-07-21 16:34:53</sys_updated_on>
    </sys_metadata_delete>
</record_update>
