<?xml version="1.0" encoding="UTF-8"?><record_update table="sys_app_scan_variable">
    <sys_app_scan_variable action="DELETE">
        <name>sys_id_21984</name>
        <original_value>9c239db880e70e108e071a9f7b7f8ef0</original_value>
        <referenced_table>sys_app</referenced_table>
        <run_script>false</run_script>
        <scan_instance>4d763b0d7fafce10695bf4e3c4753e1d</scan_instance>
        <scan_source>scan</scan_source>
        <source_id>7504eafcff5a42103ca0f6648c4fd9d8</source_id>
        <sys_class_name>sys_app_scan_variable</sys_class_name>
        <sys_created_by>jspirko</sys_created_by>
        <sys_created_on>2024-07-20 00:10:04</sys_created_on>
        <sys_id>c476eefcfb674e10808ea7e1e560f2c8</sys_id>
        <sys_mod_count>2</sys_mod_count>
        <sys_name>sys_id_21984</sys_name>
        <sys_package display_value="Pub Sector - DHS Service Desk" source="x_snc_pub_sub_dh_1">56042efcff5a42103ca0f6648c4fd93a</sys_package>
        <sys_policy/>
        <sys_scope display_value="Pub Sector - DHS Service Desk">56042efcff5a42103ca0f6648c4fd93a</sys_scope>
        <sys_update_name>sys_app_scan_variable_c476eefcfb674e10808ea7e1e560f2c8</sys_update_name>
        <sys_updated_by>jspirko</sys_updated_by>
        <sys_updated_on>2024-07-21 00:58:31</sys_updated_on>
        <template_execution_script/>
        <type display_value="Reference">242d82a65bea101001fb0c370581c7ea</type>
        <variable_hash>7dc75e186806fc02e3066ec9b128c03bdbf9bba3b459f9cdc162648800932884</variable_hash>
    </sys_app_scan_variable>
    <sys_update_version action="INSERT_OR_UPDATE">
        <action>DELETE</action>
        <application display_value="Pub Sector - DHS Service Desk">56042efcff5a42103ca0f6648c4fd93a</application>
        <file_path/>
        <instance_id>76bfb9f61ba9f594fe1b43f4bd4bcb74</instance_id>
        <instance_name>dsforum</instance_name>
        <name>sys_app_scan_variable_c476eefcfb674e10808ea7e1e560f2c8</name>
        <payload><![CDATA[<?xml version="1.0" encoding="UTF-8"?><record_update table="sys_app_scan_variable"><sys_app_scan_variable action="INSERT_OR_UPDATE"><name>sys_id_21984</name><original_value>9c239db880e70e108e071a9f7b7f8ef0</original_value><referenced_table>sys_app</referenced_table><run_script>false</run_script><scan_instance>4d763b0d7fafce10695bf4e3c4753e1d</scan_instance><scan_source>scan</scan_source><source_id>7504eafcff5a42103ca0f6648c4fd9d8</source_id><sys_class_name>sys_app_scan_variable</sys_class_name><sys_created_by>jspirko</sys_created_by><sys_created_on>2024-07-20 00:10:04</sys_created_on><sys_id>c476eefcfb674e10808ea7e1e560f2c8</sys_id><sys_mod_count>2</sys_mod_count><sys_name>sys_id_21984</sys_name><sys_package display_value="Pub Sector - DHS Service Desk" source="x_snc_pub_sub_dh_1">56042efcff5a42103ca0f6648c4fd93a</sys_package><sys_policy/><sys_scope display_value="Pub Sector - DHS Service Desk">56042efcff5a42103ca0f6648c4fd93a</sys_scope><sys_update_name>sys_app_scan_variable_c476eefcfb674e10808ea7e1e560f2c8</sys_update_name><sys_updated_by>jspirko</sys_updated_by><sys_updated_on>2024-07-21 00:58:31</sys_updated_on><template_execution_script/><type display_value="Reference">242d82a65bea101001fb0c370581c7ea</type><variable_hash>7dc75e186806fc02e3066ec9b128c03bdbf9bba3b459f9cdc162648800932884</variable_hash></sys_app_scan_variable></record_update>]]></payload>
        <payload_hash>-245639143</payload_hash>
        <record_name>sys_id_21984</record_name>
        <reverted_from/>
        <source>92042efcff5a42103ca0f6648c4fd93c</source>
        <source_table>sys_update_set</source_table>
        <state>previous</state>
        <sys_created_by>jspirko</sys_created_by>
        <sys_created_on>2024-07-21 00:58:31</sys_created_on>
        <sys_id>6f1bf38deb2302505204f635cad0cdf1</sys_id>
        <sys_mod_count>0</sys_mod_count>
        <sys_recorded_at>190d2cc20b90000001</sys_recorded_at>
        <sys_updated_by>jspirko</sys_updated_by>
        <sys_updated_on>2024-07-21 00:58:31</sys_updated_on>
        <type>Variable</type>
        <update_guid>631bf38d4723025074dfeab452db12f1</update_guid>
        <update_guid_history>631bf38d4723025074dfeab452db12f1:-245639143,3d20f349166fce10cdbe4acf8949be07:458121717,c476eefcab674e10fdb3d0eb7581b2c9:-181497970</update_guid_history>
    </sys_update_version>
    <sys_metadata_delete action="INSERT_OR_UPDATE">
        <sys_audit_delete/>
        <sys_class_name>sys_metadata_delete</sys_class_name>
        <sys_created_by>jspirko</sys_created_by>
        <sys_created_on>2024-07-21 16:45:02</sys_created_on>
        <sys_db_object display_value="" name="sys_app_scan_variable">sys_app_scan_variable</sys_db_object>
        <sys_id>3eb1aac0b4b14ed89d9a42b92be178d9</sys_id>
        <sys_metadata>c476eefcfb674e10808ea7e1e560f2c8</sys_metadata>
        <sys_mod_count>0</sys_mod_count>
        <sys_name>sys_id_21984</sys_name>
        <sys_package display_value="Pub Sector - DHS Service Desk" source="x_snc_pub_sub_dh_1">56042efcff5a42103ca0f6648c4fd93a</sys_package>
        <sys_parent/>
        <sys_policy/>
        <sys_scope display_value="Pub Sector - DHS Service Desk">56042efcff5a42103ca0f6648c4fd93a</sys_scope>
        <sys_scope_delete display_value="">27b1535901ac4ad4a151d045cd3ad1a1</sys_scope_delete>
        <sys_update_name>sys_app_scan_variable_c476eefcfb674e10808ea7e1e560f2c8</sys_update_name>
        <sys_update_version display_value="sys_app_scan_variable_c476eefcfb674e10808ea7e1e560f2c8">6f1bf38deb2302505204f635cad0cdf1</sys_update_version>
        <sys_updated_by>jspirko</sys_updated_by>
        <sys_updated_on>2024-07-21 16:45:02</sys_updated_on>
    </sys_metadata_delete>
</record_update>
