<?xml version="1.0" encoding="UTF-8"?><record_update table="sys_app_scan_variable">
    <sys_app_scan_variable action="DELETE">
        <name>sys_id_11026</name>
        <original_value>3fa77130ee2f0e102846ed44fe37afa6</original_value>
        <referenced_table>sys_app</referenced_table>
        <run_script>false</run_script>
        <scan_instance>4d763b0d7fafce10695bf4e3c4753e1d</scan_instance>
        <scan_source>scan</scan_source>
        <source_id>7504eafcff5a42103ca0f6648c4fd9d8</source_id>
        <sys_class_name>sys_app_scan_variable</sys_class_name>
        <sys_created_by>jspirko</sys_created_by>
        <sys_created_on>2024-07-19 23:55:08</sys_created_on>
        <sys_id>1103663098274e1081756f3827670256</sys_id>
        <sys_mod_count>2</sys_mod_count>
        <sys_name>sys_id_11026</sys_name>
        <sys_package display_value="Pub Sector - DHS Service Desk" source="x_snc_pub_sub_dh_1">56042efcff5a42103ca0f6648c4fd93a</sys_package>
        <sys_policy/>
        <sys_scope display_value="Pub Sector - DHS Service Desk">56042efcff5a42103ca0f6648c4fd93a</sys_scope>
        <sys_update_name>sys_app_scan_variable_1103663098274e1081756f3827670256</sys_update_name>
        <sys_updated_by>jspirko</sys_updated_by>
        <sys_updated_on>2024-07-21 00:42:28</sys_updated_on>
        <template_execution_script/>
        <type display_value="Reference">242d82a65bea101001fb0c370581c7ea</type>
        <variable_hash>42f7b8ce82cdb9dd137afc5bbb47977e8f416399d54d311ad8cebbd3cd149d5a</variable_hash>
    </sys_app_scan_variable>
    <sys_update_version action="INSERT_OR_UPDATE">
        <action>DELETE</action>
        <application display_value="Pub Sector - DHS Service Desk">56042efcff5a42103ca0f6648c4fd93a</application>
        <file_path/>
        <instance_id>76bfb9f61ba9f594fe1b43f4bd4bcb74</instance_id>
        <instance_name>dsforum</instance_name>
        <name>sys_app_scan_variable_1103663098274e1081756f3827670256</name>
        <payload><![CDATA[<?xml version="1.0" encoding="UTF-8"?><record_update table="sys_app_scan_variable"><sys_app_scan_variable action="INSERT_OR_UPDATE"><name>sys_id_11026</name><original_value>3fa77130ee2f0e102846ed44fe37afa6</original_value><referenced_table>sys_app</referenced_table><run_script>false</run_script><scan_instance>4d763b0d7fafce10695bf4e3c4753e1d</scan_instance><scan_source>scan</scan_source><source_id>7504eafcff5a42103ca0f6648c4fd9d8</source_id><sys_class_name>sys_app_scan_variable</sys_class_name><sys_created_by>jspirko</sys_created_by><sys_created_on>2024-07-19 23:55:08</sys_created_on><sys_id>1103663098274e1081756f3827670256</sys_id><sys_mod_count>2</sys_mod_count><sys_name>sys_id_11026</sys_name><sys_package display_value="Pub Sector - DHS Service Desk" source="x_snc_pub_sub_dh_1">56042efcff5a42103ca0f6648c4fd93a</sys_package><sys_policy/><sys_scope display_value="Pub Sector - DHS Service Desk">56042efcff5a42103ca0f6648c4fd93a</sys_scope><sys_update_name>sys_app_scan_variable_1103663098274e1081756f3827670256</sys_update_name><sys_updated_by>jspirko</sys_updated_by><sys_updated_on>2024-07-21 00:42:28</sys_updated_on><template_execution_script/><type display_value="Reference">242d82a65bea101001fb0c370581c7ea</type><variable_hash>42f7b8ce82cdb9dd137afc5bbb47977e8f416399d54d311ad8cebbd3cd149d5a</variable_hash></sys_app_scan_variable></record_update>]]></payload>
        <payload_hash>2124547252</payload_hash>
        <record_name>sys_id_11026</record_name>
        <reverted_from/>
        <source>92042efcff5a42103ca0f6648c4fd93c</source>
        <source_table>sys_update_set</source_table>
        <state>previous</state>
        <sys_created_by>jspirko</sys_created_by>
        <sys_created_on>2024-07-21 00:42:28</sys_created_on>
        <sys_id>54773bc1ebefce105204f635cad0cd4b</sys_id>
        <sys_mod_count>0</sys_mod_count>
        <sys_recorded_at>190d2bd6eb30000001</sys_recorded_at>
        <sys_updated_by>jspirko</sys_updated_by>
        <sys_updated_on>2024-07-21 00:42:28</sys_updated_on>
        <type>Variable</type>
        <update_guid>58773bc1d5efce1014db0473d33a1a4a</update_guid>
        <update_guid_history>58773bc1d5efce1014db0473d33a1a4a:2124547252,426c27c93febce10de796a696b32ddba:-1466659184,11036630e6274e104ee3c9b25cdbfc57:-2106278871</update_guid_history>
    </sys_update_version>
    <sys_metadata_delete action="INSERT_OR_UPDATE">
        <sys_audit_delete/>
        <sys_class_name>sys_metadata_delete</sys_class_name>
        <sys_created_by>jspirko</sys_created_by>
        <sys_created_on>2024-07-21 16:32:37</sys_created_on>
        <sys_db_object display_value="" name="sys_app_scan_variable">sys_app_scan_variable</sys_db_object>
        <sys_id>036c756d0c884e9f802652a36fd85f91</sys_id>
        <sys_metadata>1103663098274e1081756f3827670256</sys_metadata>
        <sys_mod_count>0</sys_mod_count>
        <sys_name>sys_id_11026</sys_name>
        <sys_package display_value="Pub Sector - DHS Service Desk" source="x_snc_pub_sub_dh_1">56042efcff5a42103ca0f6648c4fd93a</sys_package>
        <sys_parent/>
        <sys_policy/>
        <sys_scope display_value="Pub Sector - DHS Service Desk">56042efcff5a42103ca0f6648c4fd93a</sys_scope>
        <sys_scope_delete display_value="">27b1535901ac4ad4a151d045cd3ad1a1</sys_scope_delete>
        <sys_update_name>sys_app_scan_variable_1103663098274e1081756f3827670256</sys_update_name>
        <sys_update_version display_value="sys_app_scan_variable_1103663098274e1081756f3827670256">54773bc1ebefce105204f635cad0cd4b</sys_update_version>
        <sys_updated_by>jspirko</sys_updated_by>
        <sys_updated_on>2024-07-21 16:32:37</sys_updated_on>
    </sys_metadata_delete>
</record_update>
