<?xml version="1.0" encoding="UTF-8"?><record_update table="sys_app_scan_variable">
    <sys_app_scan_variable action="DELETE">
        <name>sys_id_17092</name>
        <original_value>04235db855e70e10b5a412db37ca63a0</original_value>
        <referenced_table>sys_app</referenced_table>
        <run_script>false</run_script>
        <scan_instance>4d763b0d7fafce10695bf4e3c4753e1d</scan_instance>
        <scan_source>scan</scan_source>
        <source_id>7504eafcff5a42103ca0f6648c4fd9d8</source_id>
        <sys_class_name>sys_app_scan_variable</sys_class_name>
        <sys_created_by>jspirko</sys_created_by>
        <sys_created_on>2024-07-20 00:03:37</sys_created_on>
        <sys_id>61f42ab02b674e10f4cfd52d2cc38760</sys_id>
        <sys_mod_count>2</sys_mod_count>
        <sys_name>sys_id_17092</sys_name>
        <sys_package display_value="Pub Sector - DHS Service Desk" source="x_snc_pub_sub_dh_1">56042efcff5a42103ca0f6648c4fd93a</sys_package>
        <sys_policy/>
        <sys_scope display_value="Pub Sector - DHS Service Desk">56042efcff5a42103ca0f6648c4fd93a</sys_scope>
        <sys_update_name>sys_app_scan_variable_61f42ab02b674e10f4cfd52d2cc38760</sys_update_name>
        <sys_updated_by>jspirko</sys_updated_by>
        <sys_updated_on>2024-07-21 00:51:38</sys_updated_on>
        <template_execution_script/>
        <type display_value="Reference">242d82a65bea101001fb0c370581c7ea</type>
        <variable_hash>2940d7fc71a183afabd995a9555bcf532a3c29eb314d62e593cb9f03777fffe3</variable_hash>
    </sys_app_scan_variable>
    <sys_update_version action="INSERT_OR_UPDATE">
        <action>DELETE</action>
        <application display_value="Pub Sector - DHS Service Desk">56042efcff5a42103ca0f6648c4fd93a</application>
        <file_path/>
        <instance_id>76bfb9f61ba9f594fe1b43f4bd4bcb74</instance_id>
        <instance_name>dsforum</instance_name>
        <name>sys_app_scan_variable_61f42ab02b674e10f4cfd52d2cc38760</name>
        <payload><![CDATA[<?xml version="1.0" encoding="UTF-8"?><record_update table="sys_app_scan_variable"><sys_app_scan_variable action="INSERT_OR_UPDATE"><name>sys_id_17092</name><original_value>04235db855e70e10b5a412db37ca63a0</original_value><referenced_table>sys_app</referenced_table><run_script>false</run_script><scan_instance>4d763b0d7fafce10695bf4e3c4753e1d</scan_instance><scan_source>scan</scan_source><source_id>7504eafcff5a42103ca0f6648c4fd9d8</source_id><sys_class_name>sys_app_scan_variable</sys_class_name><sys_created_by>jspirko</sys_created_by><sys_created_on>2024-07-20 00:03:37</sys_created_on><sys_id>61f42ab02b674e10f4cfd52d2cc38760</sys_id><sys_mod_count>2</sys_mod_count><sys_name>sys_id_17092</sys_name><sys_package display_value="Pub Sector - DHS Service Desk" source="x_snc_pub_sub_dh_1">56042efcff5a42103ca0f6648c4fd93a</sys_package><sys_policy/><sys_scope display_value="Pub Sector - DHS Service Desk">56042efcff5a42103ca0f6648c4fd93a</sys_scope><sys_update_name>sys_app_scan_variable_61f42ab02b674e10f4cfd52d2cc38760</sys_update_name><sys_updated_by>jspirko</sys_updated_by><sys_updated_on>2024-07-21 00:51:38</sys_updated_on><template_execution_script/><type display_value="Reference">242d82a65bea101001fb0c370581c7ea</type><variable_hash>2940d7fc71a183afabd995a9555bcf532a3c29eb314d62e593cb9f03777fffe3</variable_hash></sys_app_scan_variable></record_update>]]></payload>
        <payload_hash>-492127904</payload_hash>
        <record_name>sys_id_17092</record_name>
        <reverted_from/>
        <source>92042efcff5a42103ca0f6648c4fd93c</source>
        <source_table>sys_update_set</source_table>
        <state>previous</state>
        <sys_created_by>jspirko</sys_created_by>
        <sys_created_on>2024-07-21 00:51:38</sys_created_on>
        <sys_id>3a897f81eb2302505204f635cad0cd6f</sys_id>
        <sys_mod_count>0</sys_mod_count>
        <sys_recorded_at>190d2c5d5440000001</sys_recorded_at>
        <sys_updated_by>jspirko</sys_updated_by>
        <sys_updated_on>2024-07-21 00:51:38</sys_updated_on>
        <type>Variable</type>
        <update_guid>3e897f81cd2302508e1d9fe5ffab346e</update_guid>
        <update_guid_history>3e897f81cd2302508e1d9fe5ffab346e:-492127904,af8e638d8b2fce10e57344ac63bf0786:211632956,61f42ab0bd674e10795ef506f2e79b61:-427986731</update_guid_history>
    </sys_update_version>
    <sys_metadata_delete action="INSERT_OR_UPDATE">
        <sys_audit_delete/>
        <sys_class_name>sys_metadata_delete</sys_class_name>
        <sys_created_by>jspirko</sys_created_by>
        <sys_created_on>2024-07-21 16:38:13</sys_created_on>
        <sys_db_object display_value="" name="sys_app_scan_variable">sys_app_scan_variable</sys_db_object>
        <sys_id>ce55edaa04d5400c9121c6c489a49b21</sys_id>
        <sys_metadata>61f42ab02b674e10f4cfd52d2cc38760</sys_metadata>
        <sys_mod_count>0</sys_mod_count>
        <sys_name>sys_id_17092</sys_name>
        <sys_package display_value="Pub Sector - DHS Service Desk" source="x_snc_pub_sub_dh_1">56042efcff5a42103ca0f6648c4fd93a</sys_package>
        <sys_parent/>
        <sys_policy/>
        <sys_scope display_value="Pub Sector - DHS Service Desk">56042efcff5a42103ca0f6648c4fd93a</sys_scope>
        <sys_scope_delete display_value="">27b1535901ac4ad4a151d045cd3ad1a1</sys_scope_delete>
        <sys_update_name>sys_app_scan_variable_61f42ab02b674e10f4cfd52d2cc38760</sys_update_name>
        <sys_update_version display_value="sys_app_scan_variable_61f42ab02b674e10f4cfd52d2cc38760">3a897f81eb2302505204f635cad0cd6f</sys_update_version>
        <sys_updated_by>jspirko</sys_updated_by>
        <sys_updated_on>2024-07-21 16:38:13</sys_updated_on>
    </sys_metadata_delete>
</record_update>
