<?xml version="1.0" encoding="UTF-8"?><record_update table="sys_app_scan_variable">
    <sys_app_scan_variable action="DELETE">
        <name>sys_id_39</name>
        <original_value>dd6b2d76eb9202505204f635cad0cd55</original_value>
        <referenced_table>sys_app</referenced_table>
        <run_script>false</run_script>
        <scan_instance>2c2f1e1072d7061086eaa13ea8f808af</scan_instance>
        <scan_source>scan</scan_source>
        <source_id>7504eafcff5a42103ca0f6648c4fd9d8</source_id>
        <sys_class_name>sys_app_scan_variable</sys_class_name>
        <sys_created_by>jspirko</sys_created_by>
        <sys_created_on>2024-05-24 23:10:24</sys_created_on>
        <sys_id>88cff97e131602507dabdbce125ed5f5</sys_id>
        <sys_mod_count>17</sys_mod_count>
        <sys_name>sys_id_39</sys_name>
        <sys_package display_value="Pub Sector - DHS Service Desk" source="x_snc_pub_sub_dh_1">56042efcff5a42103ca0f6648c4fd93a</sys_package>
        <sys_policy/>
        <sys_scope display_value="Pub Sector - DHS Service Desk">56042efcff5a42103ca0f6648c4fd93a</sys_scope>
        <sys_update_name>sys_app_scan_variable_88cff97e131602507dabdbce125ed5f5</sys_update_name>
        <sys_updated_by>jspirko</sys_updated_by>
        <sys_updated_on>2024-07-06 00:06:16</sys_updated_on>
        <template_execution_script/>
        <type display_value="Reference">242d82a65bea101001fb0c370581c7ea</type>
        <variable_hash>3f8e0a560c8a278f8b6219344ecd329bb81956389f4d5bc13f585dcc0bb8e9e0</variable_hash>
    </sys_app_scan_variable>
    <sys_update_version action="INSERT_OR_UPDATE">
        <action>DELETE</action>
        <application display_value="Pub Sector - DHS Service Desk">56042efcff5a42103ca0f6648c4fd93a</application>
        <file_path/>
        <instance_id>76bfb9f61ba9f594fe1b43f4bd4bcb74</instance_id>
        <instance_name>dsforum</instance_name>
        <name>sys_app_scan_variable_88cff97e131602507dabdbce125ed5f5</name>
        <payload><![CDATA[<?xml version="1.0" encoding="UTF-8"?><record_update table="sys_app_scan_variable"><sys_app_scan_variable action="INSERT_OR_UPDATE"><name>sys_id_39</name><original_value>dd6b2d76eb9202505204f635cad0cd55</original_value><referenced_table>sys_app</referenced_table><run_script>false</run_script><scan_instance>2c2f1e1072d7061086eaa13ea8f808af</scan_instance><scan_source>scan</scan_source><source_id>7504eafcff5a42103ca0f6648c4fd9d8</source_id><sys_class_name>sys_app_scan_variable</sys_class_name><sys_created_by>jspirko</sys_created_by><sys_created_on>2024-05-24 23:10:24</sys_created_on><sys_id>88cff97e131602507dabdbce125ed5f5</sys_id><sys_mod_count>17</sys_mod_count><sys_name>sys_id_39</sys_name><sys_package display_value="Pub Sector - DHS Service Desk" source="x_snc_pub_sub_dh_1">56042efcff5a42103ca0f6648c4fd93a</sys_package><sys_policy/><sys_scope display_value="Pub Sector - DHS Service Desk">56042efcff5a42103ca0f6648c4fd93a</sys_scope><sys_update_name>sys_app_scan_variable_88cff97e131602507dabdbce125ed5f5</sys_update_name><sys_updated_by>jspirko</sys_updated_by><sys_updated_on>2024-07-06 00:06:16</sys_updated_on><template_execution_script/><type display_value="Reference">242d82a65bea101001fb0c370581c7ea</type><variable_hash>3f8e0a560c8a278f8b6219344ecd329bb81956389f4d5bc13f585dcc0bb8e9e0</variable_hash></sys_app_scan_variable></record_update>]]></payload>
        <payload_hash>-230458697</payload_hash>
        <record_name>sys_id_39</record_name>
        <reverted_from/>
        <source>92042efcff5a42103ca0f6648c4fd93c</source>
        <source_table>sys_update_set</source_table>
        <state>previous</state>
        <sys_created_by>jspirko</sys_created_by>
        <sys_created_on>2024-07-06 00:06:16</sys_created_on>
        <sys_id>f34f9690ffd706103ca0f6648c4fd931</sys_id>
        <sys_mod_count>0</sys_mod_count>
        <sys_recorded_at>190855ce59a0000001</sys_recorded_at>
        <sys_updated_by>jspirko</sys_updated_by>
        <sys_updated_on>2024-07-06 00:06:16</sys_updated_on>
        <type>Variable</type>
        <update_guid>f74f969012d70610a4cf1bd7ac540630</update_guid>
        <update_guid_history>f74f969012d70610a4cf1bd7ac540630:-230458697,ccd8d61c8e570610ab578d74a79fe64f:848214697,26961294055706106447ffddc78d31a3:-1665503312,539d310c35d78210c7b451c0a6e04cec:882005879,cc93ac07fd0b42103add2ab157786511:-71154699,07f592ba244b0210d6c8df98cdb22cf0:-1065449167,991c189ada4b029015bccbb9cf9dc636:1734209648,d5dc6542e507cad05e72cb029f72d02c:752921107,9ba6050e81cf8ad0e165d0f324107806:-825199176,5815362c6bf64a5027473d75bb657d67:458513377,01843d9374e2ce10477855b46d611551:120599420,761f75c772568250ee1f5337c0739b80:-1291251297,1dfe47b61dde02504ce2248645c15621:-1576644032,63bc4f321dde0250d4e18a690ca30744:-42783705,2ee7cf76ca9e025057a3b2519fca62d4:1981848886,3f074bf2779e0250ba92ef0f58684836:-364892553,edd4523ecfd602500a6d7d074caed49a:156957976,c4cff97e0a160250002a2c14414dfdf6:247218956</update_guid_history>
    </sys_update_version>
    <sys_metadata_delete action="INSERT_OR_UPDATE">
        <sys_audit_delete/>
        <sys_class_name>sys_metadata_delete</sys_class_name>
        <sys_created_by>jspirko</sys_created_by>
        <sys_created_on>2024-07-07 19:59:42</sys_created_on>
        <sys_db_object display_value="" name="sys_app_scan_variable">sys_app_scan_variable</sys_db_object>
        <sys_id>0892d9886af24fc484b7bec45ee8c104</sys_id>
        <sys_metadata>88cff97e131602507dabdbce125ed5f5</sys_metadata>
        <sys_mod_count>0</sys_mod_count>
        <sys_name>sys_id_39</sys_name>
        <sys_package display_value="Pub Sector - DHS Service Desk" source="x_snc_pub_sub_dh_1">56042efcff5a42103ca0f6648c4fd93a</sys_package>
        <sys_parent/>
        <sys_policy/>
        <sys_scope display_value="Pub Sector - DHS Service Desk">56042efcff5a42103ca0f6648c4fd93a</sys_scope>
        <sys_scope_delete display_value="">27b1535901ac4ad4a151d045cd3ad1a1</sys_scope_delete>
        <sys_update_name>sys_app_scan_variable_88cff97e131602507dabdbce125ed5f5</sys_update_name>
        <sys_update_version display_value="sys_app_scan_variable_88cff97e131602507dabdbce125ed5f5">f34f9690ffd706103ca0f6648c4fd931</sys_update_version>
        <sys_updated_by>jspirko</sys_updated_by>
        <sys_updated_on>2024-07-07 19:59:42</sys_updated_on>
    </sys_metadata_delete>
</record_update>
