<?xml version="1.0" encoding="UTF-8"?><record_update table="sys_app_scan_variable">
    <sys_app_scan_variable action="DELETE">
        <name>sys_id_25764</name>
        <original_value>32771ee7e2778e1091da6863bebd0313</original_value>
        <referenced_table>sys_app</referenced_table>
        <run_script>false</run_script>
        <scan_instance>a92aef701e005a5089733b8f5bbce75e</scan_instance>
        <scan_source>scan</scan_source>
        <source_id>7504eafcff5a42103ca0f6648c4fd9d8</source_id>
        <sys_class_name>sys_app_scan_variable</sys_class_name>
        <sys_created_by>jspirko</sys_created_by>
        <sys_created_on>2024-08-09 22:30:35</sys_created_on>
        <sys_id>7b0992e3a5bf8e10f45a320ba50d1dd1</sys_id>
        <sys_mod_count>4</sys_mod_count>
        <sys_name>sys_id_25764</sys_name>
        <sys_package display_value="Pub Sector - DHS Service Desk" source="x_snc_pub_sub_dh_1">56042efcff5a42103ca0f6648c4fd93a</sys_package>
        <sys_policy/>
        <sys_scope display_value="Pub Sector - DHS Service Desk">56042efcff5a42103ca0f6648c4fd93a</sys_scope>
        <sys_update_name>sys_app_scan_variable_7b0992e3a5bf8e10f45a320ba50d1dd1</sys_update_name>
        <sys_updated_by>jspirko</sys_updated_by>
        <sys_updated_on>2024-08-14 01:59:19</sys_updated_on>
        <template_execution_script/>
        <type display_value="Reference">242d82a65bea101001fb0c370581c7ea</type>
        <variable_hash>c19f22f54646f91d98c1b74f3f2d56bc99b168775d72a3434d083aca8c0b9468</variable_hash>
    </sys_app_scan_variable>
    <sys_update_version action="INSERT_OR_UPDATE">
        <action>DELETE</action>
        <application display_value="Pub Sector - DHS Service Desk">56042efcff5a42103ca0f6648c4fd93a</application>
        <file_path/>
        <instance_id>76bfb9f61ba9f594fe1b43f4bd4bcb74</instance_id>
        <instance_name>dsforum</instance_name>
        <name>sys_app_scan_variable_7b0992e3a5bf8e10f45a320ba50d1dd1</name>
        <payload><![CDATA[<?xml version="1.0" encoding="UTF-8"?><record_update table="sys_app_scan_variable"><sys_app_scan_variable action="INSERT_OR_UPDATE"><name>sys_id_25764</name><original_value>32771ee7e2778e1091da6863bebd0313</original_value><referenced_table>sys_app</referenced_table><run_script>false</run_script><scan_instance>a92aef701e005a5089733b8f5bbce75e</scan_instance><scan_source>scan</scan_source><source_id>7504eafcff5a42103ca0f6648c4fd9d8</source_id><sys_class_name>sys_app_scan_variable</sys_class_name><sys_created_by>jspirko</sys_created_by><sys_created_on>2024-08-09 22:30:35</sys_created_on><sys_id>7b0992e3a5bf8e10f45a320ba50d1dd1</sys_id><sys_mod_count>4</sys_mod_count><sys_name>sys_id_25764</sys_name><sys_package display_value="Pub Sector - DHS Service Desk" source="x_snc_pub_sub_dh_1">56042efcff5a42103ca0f6648c4fd93a</sys_package><sys_policy/><sys_scope display_value="Pub Sector - DHS Service Desk">56042efcff5a42103ca0f6648c4fd93a</sys_scope><sys_update_name>sys_app_scan_variable_7b0992e3a5bf8e10f45a320ba50d1dd1</sys_update_name><sys_updated_by>jspirko</sys_updated_by><sys_updated_on>2024-08-14 01:59:19</sys_updated_on><template_execution_script/><type display_value="Reference">242d82a65bea101001fb0c370581c7ea</type><variable_hash>c19f22f54646f91d98c1b74f3f2d56bc99b168775d72a3434d083aca8c0b9468</variable_hash></sys_app_scan_variable></record_update>]]></payload>
        <payload_hash>1612724233</payload_hash>
        <record_name>sys_id_25764</record_name>
        <reverted_from/>
        <source>92042efcff5a42103ca0f6648c4fd93c</source>
        <source_table>sys_update_set</source_table>
        <state>previous</state>
        <sys_created_by>jspirko</sys_created_by>
        <sys_created_on>2024-08-14 01:59:19</sys_created_on>
        <sys_id>983f6ff0eb805a505204f635cad0cd5b</sys_id>
        <sys_mod_count>0</sys_mod_count>
        <sys_recorded_at>1914e9c6b840000001</sys_recorded_at>
        <sys_updated_by>jspirko</sys_updated_by>
        <sys_updated_on>2024-08-14 01:59:19</sys_updated_on>
        <type>Variable</type>
        <update_guid>9c3f6ff031805a50d686c2d9b7f3985a</update_guid>
        <update_guid_history>9c3f6ff031805a50d686c2d9b7f3985a:1612724233,ad4c11d4b2801650f7538da578574afb:265332276,39af14cc81c85250989bd5844c9179d7:-96500300,47bcd88008c85250ae0f616fd6211383:190104317,7b0992e366bf8e103208351474ad22d2:746654902</update_guid_history>
    </sys_update_version>
    <sys_metadata_delete action="INSERT_OR_UPDATE">
        <sys_audit_delete/>
        <sys_class_name>sys_metadata_delete</sys_class_name>
        <sys_created_by>jspirko</sys_created_by>
        <sys_created_on>2024-08-14 05:14:42</sys_created_on>
        <sys_db_object display_value="" name="sys_app_scan_variable">sys_app_scan_variable</sys_db_object>
        <sys_id>1bf5b5f1506744df8e7f6995355f3a69</sys_id>
        <sys_metadata>7b0992e3a5bf8e10f45a320ba50d1dd1</sys_metadata>
        <sys_mod_count>0</sys_mod_count>
        <sys_name>sys_id_25764</sys_name>
        <sys_package display_value="Pub Sector - DHS Service Desk" source="x_snc_pub_sub_dh_1">56042efcff5a42103ca0f6648c4fd93a</sys_package>
        <sys_parent/>
        <sys_policy/>
        <sys_scope display_value="Pub Sector - DHS Service Desk">56042efcff5a42103ca0f6648c4fd93a</sys_scope>
        <sys_scope_delete display_value="">27b1535901ac4ad4a151d045cd3ad1a1</sys_scope_delete>
        <sys_update_name>sys_app_scan_variable_7b0992e3a5bf8e10f45a320ba50d1dd1</sys_update_name>
        <sys_update_version display_value="sys_app_scan_variable_7b0992e3a5bf8e10f45a320ba50d1dd1">983f6ff0eb805a505204f635cad0cd5b</sys_update_version>
        <sys_updated_by>jspirko</sys_updated_by>
        <sys_updated_on>2024-08-14 05:14:42</sys_updated_on>
    </sys_metadata_delete>
</record_update>
